{
  "packageUUID": "65f1a5a6eab674621f2500cc",
  "moduleUUID": "65f1a5bfeab674621f2500da",
  "type": "JS_MODULE",
  "unpublishedModuleInstance": {
    "version": "0.0.7",
    "name": "JSModule1_1",
    "contextType": "PAGE",
    "pageId": "Page1",
    "inputs": {},
    "jsonPathKeys": [],
    "isValid": true,
    "invalids": [
      "Module instance does not have a valid module reference in the workspace. Please update the existing package \"New Untitled Package 1 W. publish\" with module JSModule1 to resolve this issue."
    ],
    "invalidState": {
      "packageName": "New Untitled Package 1 W. publish",
      "moduleName": "JSModule1",
      "originPackageId": "65f2982b0b28202f72200468"
    },
    "userPermissions": []
  },
  "id": "Page1_JSModule1_1",
  "deleted": false,
  "gitSyncId": "65f1a618eab674621f250109_65f1a624eab674621f25011a"
}